blindtex/__init__.py
blindtex/blindtexGUI.py
blindtex/mainBlindtex.py
blindtex/tex2all.py
blindtex/gui/__init__.py
blindtex/gui/dictionariesGUI.py
blindtex/gui/mainGUI.py
blindtex/gui/mainGUIController.py
blindtex/interpreter/__init__.py
blindtex/interpreter/dictionary.py
blindtex/interpreter/reader.py
blindtex/iotools/__init__.py
blindtex/iotools/file.py
blindtex/iotools/iotools.py
blindtex/iotools/stringtools.py
blindtex/lang/__init__.py
blindtex/lang/translator.py
blindtex/lang/dicts/Accents.json
blindtex/lang/dicts/Arrows.json
blindtex/lang/dicts/BinaryOperators.json
blindtex/lang/dicts/BinaryRelations.json
blindtex/lang/dicts/Delimiters.json
blindtex/lang/dicts/Dots.json
blindtex/lang/dicts/LargeOperators.json
blindtex/lang/dicts/MathFunctions.json
blindtex/lang/dicts/Ordinary.json
blindtex/lang/dicts/Styles.json
blindtex/lang/dicts/UserDict.json
blindtex/lang/dicts/regexes.json
blindtex/lang/dicts/spanish.json
blindtex/lang/dicts/spanish.yaml
blindtex/latex2ast/__init__.py
blindtex/latex2ast/converter.py
blindtex/latex2ast/lexer.py
blindtex/latex2ast/math_object.py
blindtex/latex2ast/parser.py
blindtex/latex2ast/parsetab.py
blindtex-0.0.2.dist-info/METADATA
blindtex-0.0.2.dist-info/RECORD
blindtex-0.0.2.dist-info/WHEEL
blindtex-0.0.2.dist-info/entry_points.txt
blindtex-0.0.2.dist-info/top_level.txt
