Metadata-Version: 2.1
Name: blindtex
Version: 0.0.2
Summary: A package for converter LaTeX equations to natural language and more!.
Home-page: https://github.com/blindtex/blindtex/
Author: BlindTeX Team
Author-email: blindtexunal@gmail.com
License: UNKNOWN
Platform: UNKNOWN
Classifier: Programming Language :: Python :: 3
Classifier: License :: OSI Approved :: Apache Software License
Classifier: Operating System :: OS Independent
Provides-Extra: test
Requires-Dist: ply (==3.11)
Provides-Extra: test
Requires-Dist: pytest (==3.6.3); extra == 'test'
